lg_agents/__init__.py
lg_agents/python_toolkit.py
lg_agents/sql_code_agent.py
lg_agents/utils.py
lg_agents/code_runner/Dockerfile
lg_agents/code_runner/docker-compose.yml
lg_agents/code_runner/requirements.txt
lg_agents/legacy/interactive-simple.py
lg_agents/legacy/main_direct.py
lg_agents/legacy/sql_direct_agent.py
lg_agents-0.0.14.dist-info/METADATA
lg_agents-0.0.14.dist-info/WHEEL
lg_agents-0.0.14.dist-info/licenses/LICENSE
lg_agents-0.0.14.dist-info/RECORD
